{
  "npc_beard_man": {
	"first_interaction": [
	  {
		"speaker": "Jacob",
		"text": "Hello! Parang ngayon lang kita nakita dito. May kailangan ka ba o nag-eexplore ka lang?"
	  },
	  {
		"speaker": "Jacob",
		"text": "Kung may problema ka o may gusto kang malaman, huwag kang mahihiyang sabihin sa akin."
	  }
	],
	"repeated_interaction": [
	  {
		"speaker": "Jacob",
		"text": "Uy, ikaw na naman! Kumusta ang araw mo?"
	  },
	  {
		"speaker": "Jacob",
		"text": "Huwag kang mahihiya, sabihin mo lang kung may kailangan ka pa."
	  }
	]
  }
}
